README.rst
configi.py
setup.py
configi.egg-info/PKG-INFO
configi.egg-info/SOURCES.txt
configi.egg-info/dependency_links.txt
configi.egg-info/requires.txt
configi.egg-info/top_level.txt