Metadata-Version: 1.0
Name: configi
Version: 0.0.1
Summary: Configi is a straightforward wrapper for configuration data. It provides a consistent interface to a number of back-ends, currently via arbitrary HTTP JSON loading, Redis K/V store, and S3 JSON file loading.
Home-page: https://github.com/josefdlange/configi
Author: Josef Lange
Author-email: josef.d.lange@me.com
License: MIT
Platform: UNKNOWN
